{
  "/": {
    "status": 401,
    "contentType": "text/html; charset=utf-8",
    "size": 13416,
    "hasReact": false,
    "hasAuth": true,
    "preview": "<!doctype html><html lang=en><meta charset=utf-8><meta name=viewport content=\"width=device-width,initial-scale=1\"><title>Authentication Required</title><style>/*!normalize.css v8.0.1 | MIT License | g"
  },
  "/services": {
    "status": 401,
    "contentType": "text/html; charset=utf-8",
    "size": 13440,
    "hasReact": false,
    "hasAuth": true,
    "preview": "<!doctype html><html lang=en><meta charset=utf-8><meta name=viewport content=\"width=device-width,initial-scale=1\"><title>Authentication Required</title><style>/*!normalize.css v8.0.1 | MIT License | g"
  },
  "/about": {
    "status": 401,
    "contentType": "text/html; charset=utf-8",
    "size": 13431,
    "hasReact": false,
    "hasAuth": true,
    "preview": "<!doctype html><html lang=en><meta charset=utf-8><meta name=viewport content=\"width=device-width,initial-scale=1\"><title>Authentication Required</title><style>/*!normalize.css v8.0.1 | MIT License | g"
  },
  "/contact": {
    "status": 401,
    "contentType": "text/html; charset=utf-8",
    "size": 13437,
    "hasReact": false,
    "hasAuth": true,
    "preview": "<!doctype html><html lang=en><meta charset=utf-8><meta name=viewport content=\"width=device-width,initial-scale=1\"><title>Authentication Required</title><style>/*!normalize.css v8.0.1 | MIT License | g"
  },
  "/questionnaire": {
    "status": 401,
    "contentType": "text/html; charset=utf-8",
    "size": 13455,
    "hasReact": false,
    "hasAuth": true,
    "preview": "<!doctype html><html lang=en><meta charset=utf-8><meta name=viewport content=\"width=device-width,initial-scale=1\"><title>Authentication Required</title><style>/*!normalize.css v8.0.1 | MIT License | g"
  },
  "/admin": {
    "status": 401,
    "contentType": "text/html; charset=utf-8",
    "size": 13431,
    "hasReact": false,
    "hasAuth": true,
    "preview": "<!doctype html><html lang=en><meta charset=utf-8><meta name=viewport content=\"width=device-width,initial-scale=1\"><title>Authentication Required</title><style>/*!normalize.css v8.0.1 | MIT License | g"
  },
  "/login": {
    "status": 401,
    "contentType": "text/html; charset=utf-8",
    "size": 13431,
    "hasReact": false,
    "hasAuth": true,
    "preview": "<!doctype html><html lang=en><meta charset=utf-8><meta name=viewport content=\"width=device-width,initial-scale=1\"><title>Authentication Required</title><style>/*!normalize.css v8.0.1 | MIT License | g"
  },
  "/api/questionnaire": {
    "status": 401,
    "contentType": "text/html; charset=utf-8",
    "size": 13473,
    "hasReact": false,
    "hasAuth": true,
    "preview": "<!doctype html><html lang=en><meta charset=utf-8><meta name=viewport content=\"width=device-width,initial-scale=1\"><title>Authentication Required</title><style>/*!normalize.css v8.0.1 | MIT License | g"
  },
  "/api/color-analysis": {
    "status": 401,
    "contentType": "text/html; charset=utf-8",
    "size": 13476,
    "hasReact": false,
    "hasAuth": true,
    "preview": "<!doctype html><html lang=en><meta charset=utf-8><meta name=viewport content=\"width=device-width,initial-scale=1\"><title>Authentication Required</title><style>/*!normalize.css v8.0.1 | MIT License | g"
  },
  "/api/create-payment": {
    "status": 401,
    "contentType": "text/html; charset=utf-8",
    "size": 13476,
    "hasReact": false,
    "hasAuth": true,
    "preview": "<!doctype html><html lang=en><meta charset=utf-8><meta name=viewport content=\"width=device-width,initial-scale=1\"><title>Authentication Required</title><style>/*!normalize.css v8.0.1 | MIT License | g"
  },
  "/_next/static/css": {
    "status": 401,
    "contentType": "text/html; charset=utf-8",
    "size": 13476,
    "hasReact": false,
    "hasAuth": true,
    "preview": "<!doctype html><html lang=en><meta charset=utf-8><meta name=viewport content=\"width=device-width,initial-scale=1\"><title>Authentication Required</title><style>/*!normalize.css v8.0.1 | MIT License | g"
  },
  "/_next/static/js": {
    "status": 401,
    "contentType": "text/html; charset=utf-8",
    "size": 13473,
    "hasReact": false,
    "hasAuth": true,
    "preview": "<!doctype html><html lang=en><meta charset=utf-8><meta name=viewport content=\"width=device-width,initial-scale=1\"><title>Authentication Required</title><style>/*!normalize.css v8.0.1 | MIT License | g"
  }
}